setup.py
dsnd_distributions_3502/Binomialdistribution.py
dsnd_distributions_3502/Gaussiandistribution.py
dsnd_distributions_3502/Generaldistribution.py
dsnd_distributions_3502/__init__.py
dsnd_distributions_3502.egg-info/PKG-INFO
dsnd_distributions_3502.egg-info/SOURCES.txt
dsnd_distributions_3502.egg-info/dependency_links.txt
dsnd_distributions_3502.egg-info/not-zip-safe
dsnd_distributions_3502.egg-info/top_level.txt