Metadata-Version: 1.0
Name: dsnd-distributions-3502
Version: 0.1
Summary: Gaussian and Binomial distributions
Home-page: UNKNOWN
Author: Mehdi Zarei
Author-email: mehdy.zar@gmail.com
License: UNKNOWN
Platform: UNKNOWN
